.dockerignore
.gitignore
Dockerfile
README.md
setup.py
silph.models.egg-info/PKG-INFO
silph.models.egg-info/SOURCES.txt
silph.models.egg-info/dependency_links.txt
silph.models.egg-info/namespace_packages.txt
silph.models.egg-info/requires.txt
silph.models.egg-info/top_level.txt
silph/ext/__init__.py
silph/ext/database.py
silph/models/__init__.py
silph/models/arena.py
silph/models/base.py
silph/models/communities.py
silph/models/events.py
silph/models/logs.py
silph/models/maps.py
silph/models/meetings.py
silph/models/nests.py
silph/models/news.py
silph/models/pokemon.py
silph/models/research.py
silph/models/users.py