Metadata-Version: 1.1
Name: silph.models
Version: 0.18.2
Summary: Database models for TSR
Home-page: UNKNOWN
Author: Marco Ceppi
Author-email: marco@thesilphroad.com
License: other
Platform: UNKNOWN
Classifier: License :: Other/Proprietary License
Classifier: Topic :: Database
Classifier: Development Status :: 5 - Production/Stable
